<?xml version="1.0" encoding="utf-8"?>
<!-- 性能测试用批量配置 -->
<Root>
  <ConfigItem cls="PerfConfig10" id="perf10_0503_0">
    <Id>TestConfigLargenum::perf10_0503_0</Id>
    <Name>Item_perf10_0503_0</Name>
    <Level>45</Level>
    <Tags>9</Tags>
  </ConfigItem>
  <ConfigItem cls="PerfConfig10" id="perf10_0503_1">
    <Id>TestConfigLargenum::perf10_0503_1</Id>
    <Name>Item_perf10_0503_1</Name>
    <Level>30</Level>
    <Tags>14</Tags>
    <Tags>5</Tags>
  </ConfigItem>
  <ConfigItem cls="PerfConfig10" id="perf10_0503_2">
    <Id>TestConfigLargenum::perf10_0503_2</Id>
    <Name>Item_perf10_0503_2</Name>
    <Level>22</Level>
    <Tags>8</Tags>
    <Tags>11</Tags>
    <Tags>15</Tags>
    <Tags>5</Tags>
  </ConfigItem>
  <ConfigItem cls="PerfConfig10" id="perf10_0503_3">
    <Id>TestConfigLargenum::perf10_0503_3</Id>
    <Name>Item_perf10_0503_3</Name>
    <Level>40</Level>
    <Tags>1</Tags>
  </ConfigItem>
  <ConfigItem cls="PerfConfig10" id="perf10_0503_4">
    <Id>TestConfigLargenum::perf10_0503_4</Id>
    <Name>Item_perf10_0503_4</Name>
    <Level>33</Level>
    <Tags>4</Tags>
    <Tags>12</Tags>
  </ConfigItem>
  <ConfigItem cls="PerfConfig10" id="perf10_0503_5">
    <Id>TestConfigLargenum::perf10_0503_5</Id>
    <Name>Item_perf10_0503_5</Name>
    <Level>30</Level>
    <Tags>1</Tags>
  </ConfigItem>
  <ConfigItem cls="PerfConfig10" id="perf10_0503_6">
    <Id>TestConfigLargenum::perf10_0503_6</Id>
    <Name>Item_perf10_0503_6</Name>
    <Level>15</Level>
    <Tags>14</Tags>
    <Tags>19</Tags>
    <Tags>7</Tags>
  </ConfigItem>
</Root>
