<?xml version="1.0" encoding="utf-8"?>
<!-- 性能测试用批量配置 -->
<Root>
  <ConfigItem cls="PerfConfig2" id="perf2_0041_0">
    <Id>TestConfigLargenum::perf2_0041_0</Id>
    <Name>Item_perf2_0041_0</Name>
    <Level>16</Level>
    <Tags>1</Tags>
  </ConfigItem>
  <ConfigItem cls="PerfConfig2" id="perf2_0041_1">
    <Id>TestConfigLargenum::perf2_0041_1</Id>
    <Name>Item_perf2_0041_1</Name>
    <Level>31</Level>
    <Tags>14</Tags>
    <Tags>13</Tags>
    <Tags>2</Tags>
    <Tags>15</Tags>
  </ConfigItem>
  <ConfigItem cls="PerfConfig2" id="perf2_0041_2">
    <Id>TestConfigLargenum::perf2_0041_2</Id>
    <Name>Item_perf2_0041_2</Name>
    <Level>62</Level>
    <Tags>1</Tags>
  </ConfigItem>
  <ConfigItem cls="PerfConfig2" id="perf2_0041_3">
    <Id>TestConfigLargenum::perf2_0041_3</Id>
    <Name>Item_perf2_0041_3</Name>
    <Level>42</Level>
    <Tags>1</Tags>
    <Tags>13</Tags>
    <Tags>8</Tags>
  </ConfigItem>
  <ConfigItem cls="PerfConfig2" id="perf2_0041_4">
    <Id>TestConfigLargenum::perf2_0041_4</Id>
    <Name>Item_perf2_0041_4</Name>
    <Level>69</Level>
    <Tags>12</Tags>
  </ConfigItem>
  <ConfigItem cls="PerfConfig2" id="perf2_0041_5">
    <Id>TestConfigLargenum::perf2_0041_5</Id>
    <Name>Item_perf2_0041_5</Name>
    <Level>25</Level>
    <Tags>1</Tags>
  </ConfigItem>
  <ConfigItem cls="PerfConfig2" id="perf2_0041_6">
    <Id>TestConfigLargenum::perf2_0041_6</Id>
    <Name>Item_perf2_0041_6</Name>
    <Level>76</Level>
    <Tags>18</Tags>
    <Tags>17</Tags>
    <Tags>6</Tags>
    <Tags>16</Tags>
  </ConfigItem>
  <ConfigItem cls="PerfConfig2" id="perf2_0041_7">
    <Id>TestConfigLargenum::perf2_0041_7</Id>
    <Name>Item_perf2_0041_7</Name>
    <Level>35</Level>
    <Tags>10</Tags>
  </ConfigItem>
</Root>
