<?xml version="1.0" encoding="utf-8"?>
<!-- 性能测试用批量配置 -->
<Root>
  <ConfigItem cls="PerfConfig3" id="perf3_0878_0">
    <Id>TestConfigLargenum::perf3_0878_0</Id>
    <Name>Item_perf3_0878_0</Name>
    <Level>24</Level>
    <Tags>1</Tags>
  </ConfigItem>
  <ConfigItem cls="PerfConfig3" id="perf3_0878_1">
    <Id>TestConfigLargenum::perf3_0878_1</Id>
    <Name>Item_perf3_0878_1</Name>
    <Level>63</Level>
    <Tags>10</Tags>
    <Tags>9</Tags>
    <Tags>4</Tags>
  </ConfigItem>
  <ConfigItem cls="PerfConfig3" id="perf3_0878_2">
    <Id>TestConfigLargenum::perf3_0878_2</Id>
    <Name>Item_perf3_0878_2</Name>
    <Level>96</Level>
    <Tags>14</Tags>
    <Tags>16</Tags>
    <Tags>14</Tags>
    <Tags>8</Tags>
  </ConfigItem>
  <ConfigItem cls="PerfConfig3" id="perf3_0878_3">
    <Id>TestConfigLargenum::perf3_0878_3</Id>
    <Name>Item_perf3_0878_3</Name>
    <Level>59</Level>
    <Tags>3</Tags>
    <Tags>8</Tags>
  </ConfigItem>
  <ConfigItem cls="PerfConfig3" id="perf3_0878_4">
    <Id>TestConfigLargenum::perf3_0878_4</Id>
    <Name>Item_perf3_0878_4</Name>
    <Level>72</Level>
    <Tags>11</Tags>
    <Tags>1</Tags>
    <Tags>15</Tags>
    <Tags>2</Tags>
  </ConfigItem>
  <ConfigItem cls="PerfConfig3" id="perf3_0878_5">
    <Id>TestConfigLargenum::perf3_0878_5</Id>
    <Name>Item_perf3_0878_5</Name>
    <Level>28</Level>
    <Tags>9</Tags>
    <Tags>3</Tags>
  </ConfigItem>
  <ConfigItem cls="PerfConfig3" id="perf3_0878_6">
    <Id>TestConfigLargenum::perf3_0878_6</Id>
    <Name>Item_perf3_0878_6</Name>
    <Level>71</Level>
    <Tags>14</Tags>
    <Tags>11</Tags>
    <Tags>19</Tags>
  </ConfigItem>
  <ConfigItem cls="PerfConfig3" id="perf3_0878_7">
    <Id>TestConfigLargenum::perf3_0878_7</Id>
    <Name>Item_perf3_0878_7</Name>
    <Level>53</Level>
    <Tags>18</Tags>
    <Tags>17</Tags>
    <Tags>13</Tags>
    <Tags>9</Tags>
  </ConfigItem>
  <ConfigItem cls="PerfConfig3" id="perf3_0878_8">
    <Id>TestConfigLargenum::perf3_0878_8</Id>
    <Name>Item_perf3_0878_8</Name>
    <Level>98</Level>
    <Tags>19</Tags>
    <Tags>6</Tags>
    <Tags>10</Tags>
    <Tags>4</Tags>
  </ConfigItem>
</Root>
