<?xml version="1.0" encoding="utf-8"?>
<!-- 性能测试用批量配置 -->
<Root>
  <ConfigItem cls="PerfConfig1" id="perf1_0742_0">
    <Id>TestConfigLargenum::perf1_0742_0</Id>
    <Name>Item_perf1_0742_0</Name>
    <Level>22</Level>
    <Tags>9</Tags>
  </ConfigItem>
  <ConfigItem cls="PerfConfig1" id="perf1_0742_1">
    <Id>TestConfigLargenum::perf1_0742_1</Id>
    <Name>Item_perf1_0742_1</Name>
    <Level>26</Level>
    <Tags>10</Tags>
    <Tags>7</Tags>
    <Tags>10</Tags>
    <Tags>8</Tags>
  </ConfigItem>
  <ConfigItem cls="PerfConfig1" id="perf1_0742_2">
    <Id>TestConfigLargenum::perf1_0742_2</Id>
    <Name>Item_perf1_0742_2</Name>
    <Level>29</Level>
    <Tags>1</Tags>
    <Tags>1</Tags>
    <Tags>13</Tags>
  </ConfigItem>
  <ConfigItem cls="PerfConfig1" id="perf1_0742_3">
    <Id>TestConfigLargenum::perf1_0742_3</Id>
    <Name>Item_perf1_0742_3</Name>
    <Level>19</Level>
    <Tags>2</Tags>
    <Tags>16</Tags>
    <Tags>3</Tags>
    <Tags>16</Tags>
  </ConfigItem>
  <ConfigItem cls="PerfConfig1" id="perf1_0742_4">
    <Id>TestConfigLargenum::perf1_0742_4</Id>
    <Name>Item_perf1_0742_4</Name>
    <Level>36</Level>
    <Tags>14</Tags>
    <Tags>3</Tags>
    <Tags>9</Tags>
  </ConfigItem>
  <ConfigItem cls="PerfConfig1" id="perf1_0742_5">
    <Id>TestConfigLargenum::perf1_0742_5</Id>
    <Name>Item_perf1_0742_5</Name>
    <Level>30</Level>
    <Tags>17</Tags>
  </ConfigItem>
  <ConfigItem cls="PerfConfig1" id="perf1_0742_6">
    <Id>TestConfigLargenum::perf1_0742_6</Id>
    <Name>Item_perf1_0742_6</Name>
    <Level>64</Level>
    <Tags>18</Tags>
    <Tags>19</Tags>
    <Tags>18</Tags>
  </ConfigItem>
  <ConfigItem cls="PerfConfig1" id="perf1_0742_7">
    <Id>TestConfigLargenum::perf1_0742_7</Id>
    <Name>Item_perf1_0742_7</Name>
    <Level>72</Level>
    <Tags>10</Tags>
    <Tags>12</Tags>
  </ConfigItem>
  <ConfigItem cls="PerfConfig1" id="perf1_0742_8">
    <Id>TestConfigLargenum::perf1_0742_8</Id>
    <Name>Item_perf1_0742_8</Name>
    <Level>1</Level>
    <Tags>17</Tags>
    <Tags>12</Tags>
  </ConfigItem>
  <ConfigItem cls="PerfConfig1" id="perf1_0742_9">
    <Id>TestConfigLargenum::perf1_0742_9</Id>
    <Name>Item_perf1_0742_9</Name>
    <Level>41</Level>
    <Tags>12</Tags>
    <Tags>5</Tags>
    <Tags>9</Tags>
  </ConfigItem>
  <ConfigItem cls="PerfConfig1" id="perf1_0742_10">
    <Id>TestConfigLargenum::perf1_0742_10</Id>
    <Name>Item_perf1_0742_10</Name>
    <Level>67</Level>
    <Tags>3</Tags>
    <Tags>19</Tags>
    <Tags>10</Tags>
    <Tags>14</Tags>
  </ConfigItem>
  <ConfigItem cls="PerfConfig1" id="perf1_0742_11">
    <Id>TestConfigLargenum::perf1_0742_11</Id>
    <Name>Item_perf1_0742_11</Name>
    <Level>64</Level>
    <Tags>9</Tags>
    <Tags>10</Tags>
  </ConfigItem>
  <ConfigItem cls="PerfConfig1" id="perf1_0742_12">
    <Id>TestConfigLargenum::perf1_0742_12</Id>
    <Name>Item_perf1_0742_12</Name>
    <Level>62</Level>
    <Tags>15</Tags>
  </ConfigItem>
  <ConfigItem cls="PerfConfig1" id="perf1_0742_13">
    <Id>TestConfigLargenum::perf1_0742_13</Id>
    <Name>Item_perf1_0742_13</Name>
    <Level>54</Level>
    <Tags>9</Tags>
  </ConfigItem>
  <ConfigItem cls="PerfConfig1" id="perf1_0742_14">
    <Id>TestConfigLargenum::perf1_0742_14</Id>
    <Name>Item_perf1_0742_14</Name>
    <Level>85</Level>
    <Tags>8</Tags>
    <Tags>16</Tags>
    <Tags>3</Tags>
  </ConfigItem>
  <ConfigItem cls="PerfConfig1" id="perf1_0742_15">
    <Id>TestConfigLargenum::perf1_0742_15</Id>
    <Name>Item_perf1_0742_15</Name>
    <Level>34</Level>
    <Tags>1</Tags>
  </ConfigItem>
  <ConfigItem cls="PerfConfig1" id="perf1_0742_16">
    <Id>TestConfigLargenum::perf1_0742_16</Id>
    <Name>Item_perf1_0742_16</Name>
    <Level>69</Level>
    <Tags>2</Tags>
  </ConfigItem>
</Root>
